brreg/__init__.py
brreg/_exceptions.py
brreg/enhetsregisteret/__init__.py
brreg/enhetsregisteret/_client.py
brreg/enhetsregisteret/_pagination.py
brreg/enhetsregisteret/_queries.py
brreg/enhetsregisteret/_responses.py
brreg/enhetsregisteret/_types.py
brreg-1.2.0.dist-info/LICENSE
brreg-1.2.0.dist-info/METADATA
brreg-1.2.0.dist-info/WHEEL
brreg-1.2.0.dist-info/RECORD
