Metadata-Version: 2.1
Name: brreg
Version: 1.2.0
Summary: API client for Brønnøysundregistrene.
Home-page: https://github.com/crdbrd/python-brreg
License: Apache-2.0
Keywords: brreg,enhetsregisteret
Author: Stein Magnus Jodal
Author-email: stein.magnus@jodal.no
Requires-Python: >=3.9.0,<4.0.0
Classifier: Development Status :: 5 - Production/Stable
Classifier: Intended Audience :: Developers
Classifier: License :: OSI Approved :: Apache Software License
Classifier: Programming Language :: Python :: 3
Classifier: Programming Language :: Python :: 3.9
Classifier: Programming Language :: Python :: 3.10
Classifier: Programming Language :: Python :: 3.11
Classifier: Programming Language :: Python :: 3.12
Classifier: Programming Language :: Python :: 3.13
Classifier: Topic :: Software Development :: Libraries
Requires-Dist: httpx (>=0.24)
Requires-Dist: pydantic (>=2)
Project-URL: Documentation, https://brreg.readthedocs.io
Project-URL: Repository, https://github.com/crdbrd/python-brreg
